{
  "title": "Gió mùa tây nam mạnh lên, miền Nam có mưa lớn về chiều",
  "sub_title": "TTO - Đài khí tượng thủy văn khu vực Nam Bộ cho biết gió mùa tây nam đang có xu hướng hoạt động mạnh lên trong hôm nay 21-6 và sẽ gây ra những cơn mưa lớn cho miền Nam về chiều. Còn từ sáng đến trưa, khu vực có nắng nóng oi bức, khó chịu.",
  "content": "<div class=\"content fck\" id=\"main-detail-body\">\n <div class=\"VCSortableInPreviewMode\" style=\"\" type=\"Photo\">\n  <div>\n   <img alt=\"Gió mùa tây nam mạnh lên, miền Nam có mưa lớn về chiều - Ảnh 1.\" data-original=\"https://cdn.tuoitre.vn/2021/6/21/z251169308749955a8a89732224a8d6bcd091ee96314f1-162423824866892604811.jpg\" h=\"1403\" height=\"\" id=\"img_743d38f0-d22e-11eb-a216-11d6c5036ac9\" photoid=\"743d38f0-d22e-11eb-a216-11d6c5036ac9\" rel=\"lightbox\" src=\"https://cdn.tuoitre.vn/thumb_w/586/2021/6/21/z251169308749955a8a89732224a8d6bcd091ee96314f1-162423824866892604811.jpg\" style=\"max-width:100%;\" title=\"Gió mùa tây nam mạnh lên, miền Nam có mưa lớn về chiều - Ảnh 1.\" type=\"photo\" w=\"2000\" width=\"\"/>\n  </div>\n  <div class=\"PhotoCMS_Caption\">\n   <p class=\"\" data-placeholder=\"[nhập chú thích]\">\n    Miền Nam sẽ có mưa lớn về chiều tối - Ảnh: LÊ PHAN\n   </p>\n  </div>\n </div>\n <p>\n  Theo đó, gió mùa tây nam hoạt động với cường độ tăng dần sẽ chi phối thời tiết  khu vực các tỉnh miền Nam. Song song với đó, vùng áp thấp nóng phía tây cũng đang hoạt động ổn định. Do vậy miền Nam sẽ có hai kiểu thời tiết trái ngược nhau giữa buổi sáng và chiều tối.\n </p>\n <p>\n  Từ buổi sáng đến trưa, thời tiết khu vực chủ yếu nắng, cường độ nắng tăng nhanh vào giữa trưa, một số nơi đạt mức 35 độ C như Biên Hòa, Tây Ninh, Bình Dương, TP.HCM, Vĩnh Long, Bến Tre và An Giang.\n </p>\n <p>\n  Độ ẩm không khí có phần xuống thấp dẫn tới nguy cơ cao xảy ra cháy nổ, người dân cần đề phòng chú ý. Các nơi khác nhiệt độ dao động ở mức 32-34 độ C.\n </p>\n <p>\n  Tuy nhiên thời gian nắng không kéo dài, đến đầu chiều mây dông phát triển gây mưa rào rải rác, có nơi mưa vừa, mưa to và dông. Vùng mưa lớn tập trung ở khu vực các tỉnh miền Đông như Bình Phước, Tây Ninh và Đồng Nai.\n </p>\n <p>\n  Mưa lớn có thể làm nước không thoát kịp, gây ngập cục bộ vài tuyến đường trung tâm ở các tỉnh vừa kể trên. Trong cơn mưa đề phòng kèm theo các hiện tượng thời tiết cực đoan như sấm sét, gió giật mạnh và lốc xoáy.\n </p>\n <p>\n  Càng về đêm mưa có phần giảm hơn chỉ còn ở mức vài nơi, nhiệt độ ban đêm dao động 23-26 độ C.\n </p>\n <div class=\"VCSortableInPreviewMode\" type=\"RelatedOneNews\">\n  <a data-cke-saved-href=\"https://tuoitre.vn/nang-nong-nhu-nung-nguoi-ha-noi-van-phoi-minh-muu-sinh-20210620151431005.htm\" href=\"https://tuoitre.vn/nang-nong-nhu-nung-nguoi-ha-noi-van-phoi-minh-muu-sinh-20210620151431005.htm\" style=\"padding: 0px;\">\n   <img alt=\"Nắng nóng như nung, người Hà Nội vẫn phơi mình mưu sinh\" data-cke-saved-src=\"https://cdn.tuoitre.vn/zoom/150_120/2021/6/20/dsc07713-1624176381796240453517-crop-1624176942040884727256.jpg\" src=\"https://cdn.tuoitre.vn/zoom/150_120/2021/6/20/dsc07713-1624176381796240453517-crop-1624176942040884727256.jpg\" style=\"float: left; width: 150px; height: 120px; margin-right: 10px;\"/>\n  </a>\n  <a class=\"OneNewsTitle\" data-cke-saved-href=\"https://tuoitre.vn/nang-nong-nhu-nung-nguoi-ha-noi-van-phoi-minh-muu-sinh-20210620151431005.htm\" href=\"https://tuoitre.vn/nang-nong-nhu-nung-nguoi-ha-noi-van-phoi-minh-muu-sinh-20210620151431005.htm\" style=\"text-align: left;\">\n   Nắng nóng như nung, người Hà Nội vẫn phơi mình mưu sinh\n  </a>\n  <p class=\"VCObjectBoxRelatedNewsItemSapo\">\n   TTO - Trong ngày 20-6, thời tiết tại Hà Nội ghi nhận nắng nóng đỉnh điểm, nhiệt độ cao nhất phổ biến 37-40 độ, có nơi trên 40 độ. Dù vậy, rất nhiều người lao động tại Hà Nội vẫn đội nắng ra đường chật vật mưu sinh.\n  </p>\n </div>\n</div>\n",
  "pub_date": "2021-06-21 08:54:00+07:00",
  "post_id": "2021-06-21-08-20210621081931192"
}